[
  {
    "id": "ancilla-01",
    "latin": "ancilla",
    "genitive": "ancillae",
    "gender": "f",
    "english": "slave-girl, maidservant",
    "part_of_speech": "noun",
    "declension": 1,
    "conjugation": null,
    "topics": ["family", "daily-life"],
    "frequency_rank": 5
  },
  {
    "id": "aqua-01",
    "latin": "aqua",
    "genitive": "aquae",
    "gender": "f",
    "english": "water",
    "part_of_speech": "noun",
    "declension": 1,
    "conjugation": null,
    "topics": ["daily-life", "nature"],
    "frequency_rank": 12
  },
  {
    "id": "cena-01",
    "latin": "cēna",
    "genitive": "cēnae",
    "gender": "f",
    "english": "dinner, meal",
    "part_of_speech": "noun",
    "declension": 1,
    "conjugation": null,
    "topics": ["daily-life"],
    "frequency_rank": 14
  },
  {
    "id": "copia-01",
    "latin": "cōpia",
    "genitive": "cōpiae",
    "gender": "f",
    "english": "abundance, supply; (pl.) troops",
    "part_of_speech": "noun",
    "declension": 1,
    "conjugation": null,
    "topics": ["war/army", "daily-life"],
    "frequency_rank": 30
  },
  {
    "id": "culina-01",
    "latin": "culīna",
    "genitive": "culīnae",
    "gender": "f",
    "english": "kitchen",
    "part_of_speech": "noun",
    "declension": 1,
    "conjugation": null,
    "topics": ["daily-life"],
    "frequency_rank": 38
  },
  {
    "id": "fama-01",
    "latin": "fāma",
    "genitive": "fāmae",
    "gender": "f",
    "english": "rumour, reputation, fame",
    "part_of_speech": "noun",
    "declension": 1,
    "conjugation": null,
    "topics": ["daily-life"],
    "frequency_rank": 24
  },
  {
    "id": "femina-01",
    "latin": "fēmina",
    "genitive": "fēminae",
    "gender": "f",
    "english": "woman",
    "part_of_speech": "noun",
    "declension": 1,
    "conjugation": null,
    "topics": ["family", "daily-life"],
    "frequency_rank": 3
  },
  {
    "id": "filia-01",
    "latin": "fīlia",
    "genitive": "fīliae",
    "gender": "f",
    "english": "daughter",
    "part_of_speech": "noun",
    "declension": 1,
    "conjugation": null,
    "topics": ["family"],
    "frequency_rank": 18
  },
  {
    "id": "hasta-01",
    "latin": "hasta",
    "genitive": "hastae",
    "gender": "f",
    "english": "spear",
    "part_of_speech": "noun",
    "declension": 1,
    "conjugation": null,
    "topics": ["war/army"],
    "frequency_rank": 22
  },
  {
    "id": "hora-01",
    "latin": "hōra",
    "genitive": "hōrae",
    "gender": "f",
    "english": "hour",
    "part_of_speech": "noun",
    "declension": 1,
    "conjugation": null,
    "topics": ["daily-life"],
    "frequency_rank": 40
  },
  {
    "id": "insula-01",
    "latin": "īnsula",
    "genitive": "īnsulae",
    "gender": "f",
    "english": "island",
    "part_of_speech": "noun",
    "declension": 1,
    "conjugation": null,
    "topics": ["travel", "nature"],
    "frequency_rank": 35
  },
  {
    "id": "ira-01",
    "latin": "īra",
    "genitive": "īrae",
    "gender": "f",
    "english": "anger",
    "part_of_speech": "noun",
    "declension": 1,
    "conjugation": null,
    "topics": ["daily-life"],
    "frequency_rank": 20
  },
  {
    "id": "luna-01",
    "latin": "lūna",
    "genitive": "lūnae",
    "gender": "f",
    "english": "moon",
    "part_of_speech": "noun",
    "declension": 1,
    "conjugation": null,
    "topics": ["nature", "gods"],
    "frequency_rank": 45
  },
  {
    "id": "mora-01",
    "latin": "mora",
    "genitive": "morae",
    "gender": "f",
    "english": "delay",
    "part_of_speech": "noun",
    "declension": 1,
    "conjugation": null,
    "topics": ["daily-life", "travel"],
    "frequency_rank": 16
  },
  {
    "id": "nauta-01",
    "latin": "nauta",
    "genitive": "nautae",
    "gender": "m",
    "english": "sailor",
    "part_of_speech": "noun",
    "declension": 1,
    "conjugation": null,
    "topics": ["travel", "war/army"],
    "frequency_rank": 28
  },
  {
    "id": "patria-01",
    "latin": "patria",
    "genitive": "patriae",
    "gender": "f",
    "english": "fatherland, country",
    "part_of_speech": "noun",
    "declension": 1,
    "conjugation": null,
    "topics": ["war/army", "daily-life"],
    "frequency_rank": 32
  },
  {
    "id": "poeta-01",
    "latin": "poēta",
    "genitive": "poētae",
    "gender": "m",
    "english": "poet",
    "part_of_speech": "noun",
    "declension": 1,
    "conjugation": null,
    "topics": ["daily-life"],
    "frequency_rank": 50
  },
  {
    "id": "puella-01",
    "latin": "puella",
    "genitive": "puellae",
    "gender": "f",
    "english": "girl",
    "part_of_speech": "noun",
    "declension": 1,
    "conjugation": null,
    "topics": ["family", "daily-life"],
    "frequency_rank": 4
  },
  {
    "id": "regina-01",
    "latin": "rēgīna",
    "genitive": "rēgīnae",
    "gender": "f",
    "english": "queen",
    "part_of_speech": "noun",
    "declension": 1,
    "conjugation": null,
    "topics": ["family", "gods"],
    "frequency_rank": 10
  },
  {
    "id": "silva-01",
    "latin": "silva",
    "genitive": "silvae",
    "gender": "f",
    "english": "wood, forest",
    "part_of_speech": "noun",
    "declension": 1,
    "conjugation": null,
    "topics": ["nature", "travel"],
    "frequency_rank": 26
  },
  {
    "id": "terra-01",
    "latin": "terra",
    "genitive": "terrae",
    "gender": "f",
    "english": "land, earth",
    "part_of_speech": "noun",
    "declension": 1,
    "conjugation": null,
    "topics": ["nature", "travel"],
    "frequency_rank": 15
  },
  {
    "id": "via-01",
    "latin": "via",
    "genitive": "viae",
    "gender": "f",
    "english": "road, way, street",
    "part_of_speech": "noun",
    "declension": 1,
    "conjugation": null,
    "topics": ["travel", "daily-life"],
    "frequency_rank": 11
  },
  {
    "id": "villa-01",
    "latin": "villa",
    "genitive": "villae",
    "gender": "f",
    "english": "country house, villa",
    "part_of_speech": "noun",
    "declension": 1,
    "conjugation": null,
    "topics": ["daily-life", "family"],
    "frequency_rank": 9
  },
  {
    "id": "vita-01",
    "latin": "vīta",
    "genitive": "vītae",
    "gender": "f",
    "english": "life",
    "part_of_speech": "noun",
    "declension": 1,
    "conjugation": null,
    "topics": ["daily-life"],
    "frequency_rank": 17
  },
  {
    "id": "amicus-01",
    "latin": "amīcus",
    "genitive": "amīcī",
    "gender": "m",
    "english": "friend",
    "part_of_speech": "noun",
    "declension": 2,
    "conjugation": null,
    "topics": ["daily-life", "family"],
    "frequency_rank": 8
  },
  {
    "id": "animus-01",
    "latin": "animus",
    "genitive": "animī",
    "gender": "m",
    "english": "mind, spirit, courage",
    "part_of_speech": "noun",
    "declension": 2,
    "conjugation": null,
    "topics": ["daily-life"],
    "frequency_rank": 19
  },
  {
    "id": "bellum-01",
    "latin": "bellum",
    "genitive": "bellī",
    "gender": "n",
    "english": "war",
    "part_of_speech": "noun",
    "declension": 2,
    "conjugation": null,
    "topics": ["war/army"],
    "frequency_rank": 6
  },
  {
    "id": "consilium-01",
    "latin": "cōnsilium",
    "genitive": "cōnsiliī",
    "gender": "n",
    "english": "plan, advice, counsel",
    "part_of_speech": "noun",
    "declension": 2,
    "conjugation": null,
    "topics": ["daily-life", "war/army"],
    "frequency_rank": 13
  },
  {
    "id": "cubiculum-01",
    "latin": "cubiculum",
    "genitive": "cubiculī",
    "gender": "n",
    "english": "bedroom",
    "part_of_speech": "noun",
    "declension": 2,
    "conjugation": null,
    "topics": ["daily-life"],
    "frequency_rank": 21
  },
  {
    "id": "deus-01",
    "latin": "deus",
    "genitive": "deī",
    "gender": "m",
    "english": "god",
    "part_of_speech": "noun",
    "declension": 2,
    "conjugation": null,
    "topics": ["gods"],
    "frequency_rank": 7
  },
  {
    "id": "dominus-01",
    "latin": "dominus",
    "genitive": "dominī",
    "gender": "m",
    "english": "master, lord",
    "part_of_speech": "noun",
    "declension": 2,
    "conjugation": null,
    "topics": ["family", "daily-life"],
    "frequency_rank": 7
  },
  {
    "id": "equus-01",
    "latin": "equus",
    "genitive": "equī",
    "gender": "m",
    "english": "horse",
    "part_of_speech": "noun",
    "declension": 2,
    "conjugation": null,
    "topics": ["travel", "war/army", "nature"],
    "frequency_rank": 27
  },
  {
    "id": "filius-01",
    "latin": "fīlius",
    "genitive": "fīliī",
    "gender": "m",
    "english": "son",
    "part_of_speech": "noun",
    "declension": 2,
    "conjugation": null,
    "topics": ["family"],
    "frequency_rank": 9
  },
  {
    "id": "gladius-01",
    "latin": "gladius",
    "genitive": "gladiī",
    "gender": "m",
    "english": "sword",
    "part_of_speech": "noun",
    "declension": 2,
    "conjugation": null,
    "topics": ["war/army"],
    "frequency_rank": 23
  },
  {
    "id": "imperium-01",
    "latin": "imperium",
    "genitive": "imperiī",
    "gender": "n",
    "english": "power, command, empire",
    "part_of_speech": "noun",
    "declension": 2,
    "conjugation": null,
    "topics": ["war/army", "gods"],
    "frequency_rank": 16
  },
  {
    "id": "locus-01",
    "latin": "locus",
    "genitive": "locī",
    "gender": "m",
    "english": "place",
    "part_of_speech": "noun",
    "declension": 2,
    "conjugation": null,
    "topics": ["travel", "daily-life"],
    "frequency_rank": 25
  },
  {
    "id": "ludus-01",
    "latin": "lūdus",
    "genitive": "lūdī",
    "gender": "m",
    "english": "game, school",
    "part_of_speech": "noun",
    "declension": 2,
    "conjugation": null,
    "topics": ["daily-life"],
    "frequency_rank": 42
  },
  {
    "id": "magister-01",
    "latin": "magister",
    "genitive": "magistrī",
    "gender": "m",
    "english": "schoolmaster, teacher",
    "part_of_speech": "noun",
    "declension": 2,
    "conjugation": null,
    "topics": ["daily-life"],
    "frequency_rank": 31
  },
  {
    "id": "maritus-01",
    "latin": "marītus",
    "genitive": "marītī",
    "gender": "m",
    "english": "husband",
    "part_of_speech": "noun",
    "declension": 2,
    "conjugation": null,
    "topics": ["family"],
    "frequency_rank": 15
  },
  {
    "id": "murus-01",
    "latin": "mūrus",
    "genitive": "mūrī",
    "gender": "m",
    "english": "wall",
    "part_of_speech": "noun",
    "declension": 2,
    "conjugation": null,
    "topics": ["war/army", "daily-life"],
    "frequency_rank": 24
  },
  {
    "id": "nuntius-01",
    "latin": "nūntius",
    "genitive": "nūntiī",
    "gender": "m",
    "english": "messenger, message, news",
    "part_of_speech": "noun",
    "declension": 2,
    "conjugation": null,
    "topics": ["daily-life", "war/army"],
    "frequency_rank": 29
  },
  {
    "id": "oculus-01",
    "latin": "oculus",
    "genitive": "oculī",
    "gender": "m",
    "english": "eye",
    "part_of_speech": "noun",
    "declension": 2,
    "conjugation": null,
    "topics": ["daily-life"],
    "frequency_rank": 44
  },
  {
    "id": "oppidum-01",
    "latin": "oppidum",
    "genitive": "oppidī",
    "gender": "n",
    "english": "town",
    "part_of_speech": "noun",
    "declension": 2,
    "conjugation": null,
    "topics": ["travel", "daily-life"],
    "frequency_rank": 26
  },
  {
    "id": "periculum-01",
    "latin": "perīculum",
    "genitive": "perīculī",
    "gender": "n",
    "english": "danger",
    "part_of_speech": "noun",
    "declension": 2,
    "conjugation": null,
    "topics": ["war/army", "travel"],
    "frequency_rank": 33
  },
  {
    "id": "poculum-01",
    "latin": "pōculum",
    "genitive": "pōculī",
    "gender": "n",
    "english": "cup, drink",
    "part_of_speech": "noun",
    "declension": 2,
    "conjugation": null,
    "topics": ["daily-life"],
    "frequency_rank": 36
  },
  {
    "id": "populus-01",
    "latin": "populus",
    "genitive": "populī",
    "gender": "m",
    "english": "people, nation",
    "part_of_speech": "noun",
    "declension": 2,
    "conjugation": null,
    "topics": ["daily-life", "war/army"],
    "frequency_rank": 20
  },
  {
    "id": "puer-01",
    "latin": "puer",
    "genitive": "puerī",
    "gender": "m",
    "english": "boy, child",
    "part_of_speech": "noun",
    "declension": 2,
    "conjugation": null,
    "topics": ["family", "daily-life"],
    "frequency_rank": 6
  },
  {
    "id": "servus-01",
    "latin": "servus",
    "genitive": "servī",
    "gender": "m",
    "english": "slave",
    "part_of_speech": "noun",
    "declension": 2,
    "conjugation": null,
    "topics": ["family", "daily-life"],
    "frequency_rank": 2
  },
  {
    "id": "tabernaculum-01",
    "latin": "tabernāculum",
    "genitive": "tabernāculī",
    "gender": "n",
    "english": "tent",
    "part_of_speech": "noun",
    "declension": 2,
    "conjugation": null,
    "topics": ["war/army", "travel"],
    "frequency_rank": 34
  },
  {
    "id": "templum-01",
    "latin": "templum",
    "genitive": "templī",
    "gender": "n",
    "english": "temple",
    "part_of_speech": "noun",
    "declension": 2,
    "conjugation": null,
    "topics": ["gods", "daily-life"],
    "frequency_rank": 28
  },
  {
    "id": "venenum-01",
    "latin": "venēnum",
    "genitive": "venēnī",
    "gender": "n",
    "english": "poison",
    "part_of_speech": "noun",
    "declension": 2,
    "conjugation": null,
    "topics": ["daily-life"],
    "frequency_rank": 37
  },
  {
    "id": "verbum-01",
    "latin": "verbum",
    "genitive": "verbī",
    "gender": "n",
    "english": "word",
    "part_of_speech": "noun",
    "declension": 2,
    "conjugation": null,
    "topics": ["daily-life"],
    "frequency_rank": 22
  },
  {
    "id": "vir-01",
    "latin": "vir",
    "genitive": "virī",
    "gender": "m",
    "english": "man, hero",
    "part_of_speech": "noun",
    "declension": 2,
    "conjugation": null,
    "topics": ["family", "war/army", "daily-life"],
    "frequency_rank": 8
  },
  {
    "id": "canis-01",
    "latin": "canis",
    "genitive": "canis",
    "gender": "m",
    "english": "dog",
    "part_of_speech": "noun",
    "declension": 3,
    "conjugation": null,
    "topics": ["daily-life", "nature"],
    "frequency_rank": 43
  },
  {
    "id": "civis-01",
    "latin": "cīvis",
    "genitive": "cīvis",
    "gender": "m",
    "english": "citizen",
    "part_of_speech": "noun",
    "declension": 3,
    "conjugation": null,
    "topics": ["daily-life", "war/army"],
    "frequency_rank": 39
  },
  {
    "id": "dux-01",
    "latin": "dux",
    "genitive": "ducis",
    "gender": "m",
    "english": "leader, general",
    "part_of_speech": "noun",
    "declension": 3,
    "conjugation": null,
    "topics": ["war/army"],
    "frequency_rank": 18
  },
  {
    "id": "flumen-01",
    "latin": "flūmen",
    "genitive": "flūminis",
    "gender": "n",
    "english": "river",
    "part_of_speech": "noun",
    "declension": 3,
    "conjugation": null,
    "topics": ["nature", "travel"],
    "frequency_rank": 19
  },
  {
    "id": "homo-01",
    "latin": "homō",
    "genitive": "hominis",
    "gender": "m",
    "english": "man, person, human",
    "part_of_speech": "noun",
    "declension": 3,
    "conjugation": null,
    "topics": ["daily-life"],
    "frequency_rank": 21
  },
  {
    "id": "imperator-01",
    "latin": "imperātor",
    "genitive": "imperātōris",
    "gender": "m",
    "english": "emperor, commander",
    "part_of_speech": "noun",
    "declension": 3,
    "conjugation": null,
    "topics": ["war/army", "gods"],
    "frequency_rank": 17
  },
  {
    "id": "letum-01",
    "latin": "lētum",
    "genitive": "lētī",
    "gender": "n",
    "english": "(violent) death",
    "part_of_speech": "noun",
    "declension": 2,
    "conjugation": null,
    "topics": ["war/army", "daily-life"],
    "frequency_rank": 41
  },
  {
    "id": "lex-01",
    "latin": "lēx",
    "genitive": "lēgis",
    "gender": "f",
    "english": "law",
    "part_of_speech": "noun",
    "declension": 3,
    "conjugation": null,
    "topics": ["daily-life"],
    "frequency_rank": 46
  },
  {
    "id": "lux-01",
    "latin": "lūx",
    "genitive": "lūcis",
    "gender": "f",
    "english": "light",
    "part_of_speech": "noun",
    "declension": 3,
    "conjugation": null,
    "topics": ["nature", "daily-life"],
    "frequency_rank": 47
  },
  {
    "id": "medicus-01",
    "latin": "medicus",
    "genitive": "medicī",
    "gender": "m",
    "english": "doctor, physician",
    "part_of_speech": "noun",
    "declension": 2,
    "conjugation": null,
    "topics": ["daily-life"],
    "frequency_rank": 35
  },
  {
    "id": "miles-01",
    "latin": "mīles",
    "genitive": "mīlitis",
    "gender": "m",
    "english": "soldier",
    "part_of_speech": "noun",
    "declension": 3,
    "conjugation": null,
    "topics": ["war/army"],
    "frequency_rank": 5
  },
  {
    "id": "mors-01",
    "latin": "mors",
    "genitive": "mortis",
    "gender": "f",
    "english": "death",
    "part_of_speech": "noun",
    "declension": 3,
    "conjugation": null,
    "topics": ["war/army", "daily-life"],
    "frequency_rank": 20
  },
  {
    "id": "navis-01",
    "latin": "nāvis",
    "genitive": "nāvis",
    "gender": "f",
    "english": "ship",
    "part_of_speech": "noun",
    "declension": 3,
    "conjugation": null,
    "topics": ["travel", "war/army"],
    "frequency_rank": 23
  },
  {
    "id": "nomen-01",
    "latin": "nōmen",
    "genitive": "nōminis",
    "gender": "n",
    "english": "name",
    "part_of_speech": "noun",
    "declension": 3,
    "conjugation": null,
    "topics": ["daily-life"],
    "frequency_rank": 14
  },
  {
    "id": "pars-01",
    "latin": "pars",
    "genitive": "partis",
    "gender": "f",
    "english": "part, direction",
    "part_of_speech": "noun",
    "declension": 3,
    "conjugation": null,
    "topics": ["daily-life", "travel"],
    "frequency_rank": 32
  },
  {
    "id": "pater-01",
    "latin": "pater",
    "genitive": "patris",
    "gender": "m",
    "english": "father",
    "part_of_speech": "noun",
    "declension": 3,
    "conjugation": null,
    "topics": ["family", "gods"],
    "frequency_rank": 10
  },
  {
    "id": "rex-01",
    "latin": "rēx",
    "genitive": "rēgis",
    "gender": "m",
    "english": "king",
    "part_of_speech": "noun",
    "declension": 3,
    "conjugation": null,
    "topics": ["family", "gods", "war/army"],
    "frequency_rank": 7
  },
  {
    "id": "testamentum-01",
    "latin": "testāmentum",
    "genitive": "testāmentī",
    "gender": "n",
    "english": "will, testament",
    "part_of_speech": "noun",
    "declension": 2,
    "conjugation": null,
    "topics": ["daily-life"],
    "frequency_rank": 40
  },
  {
    "id": "urbs-01",
    "latin": "urbs",
    "genitive": "urbis",
    "gender": "f",
    "english": "city",
    "part_of_speech": "noun",
    "declension": 3,
    "conjugation": null,
    "topics": ["travel", "daily-life"],
    "frequency_rank": 13
  },
  {
    "id": "uxor-01",
    "latin": "uxor",
    "genitive": "uxōris",
    "gender": "f",
    "english": "wife",
    "part_of_speech": "noun",
    "declension": 3,
    "conjugation": null,
    "topics": ["family"],
    "frequency_rank": 11
  },
  {
    "id": "vox-01",
    "latin": "vōx",
    "genitive": "vōcis",
    "gender": "f",
    "english": "voice",
    "part_of_speech": "noun",
    "declension": 3,
    "conjugation": null,
    "topics": ["daily-life"],
    "frequency_rank": 36
  },
  {
    "id": "amo-01",
    "latin": "amō",
    "genitive": null,
    "gender": null,
    "english": "I love, like",
    "part_of_speech": "verb",
    "declension": null,
    "conjugation": 1,
    "topics": ["family", "daily-life"],
    "frequency_rank": 4
  },
  {
    "id": "ambulo-01",
    "latin": "ambulō",
    "genitive": null,
    "gender": null,
    "english": "I walk",
    "part_of_speech": "verb",
    "declension": null,
    "conjugation": 1,
    "topics": ["daily-life", "travel"],
    "frequency_rank": 18
  },
  {
    "id": "appropinquo-01",
    "latin": "appropinquō",
    "genitive": null,
    "gender": null,
    "english": "I approach, draw near",
    "part_of_speech": "verb",
    "declension": null,
    "conjugation": 1,
    "topics": ["travel", "war/army"],
    "frequency_rank": 25
  },
  {
    "id": "audio-01",
    "latin": "audiō",
    "genitive": null,
    "gender": null,
    "english": "I hear, listen to",
    "part_of_speech": "verb",
    "declension": null,
    "conjugation": null,
    "topics": ["daily-life"],
    "frequency_rank": 14
  },
  {
    "id": "bibit-01",
    "latin": "bibō",
    "genitive": null,
    "gender": null,
    "english": "I drink",
    "part_of_speech": "verb",
    "declension": null,
    "conjugation": null,
    "topics": ["daily-life"],
    "frequency_rank": 33
  },
  {
    "id": "capio-01",
    "latin": "capiō",
    "genitive": null,
    "gender": null,
    "english": "I take, capture",
    "part_of_speech": "verb",
    "declension": null,
    "conjugation": null,
    "topics": ["war/army", "daily-life"],
    "frequency_rank": 10
  },
  {
    "id": "celo-01",
    "latin": "cēlō",
    "genitive": null,
    "gender": null,
    "english": "I hide, conceal",
    "part_of_speech": "verb",
    "declension": null,
    "conjugation": 1,
    "topics": ["daily-life"],
    "frequency_rank": 42
  },
  {
    "id": "clamo-01",
    "latin": "clāmō",
    "genitive": null,
    "gender": null,
    "english": "I shout, cry out",
    "part_of_speech": "verb",
    "declension": null,
    "conjugation": 1,
    "topics": ["daily-life", "war/army"],
    "frequency_rank": 19
  },
  {
    "id": "cupio-01",
    "latin": "cupiō",
    "genitive": null,
    "gender": null,
    "english": "I want, desire, wish",
    "part_of_speech": "verb",
    "declension": null,
    "conjugation": null,
    "topics": ["daily-life"],
    "frequency_rank": 12
  },
  {
    "id": "delet-01",
    "latin": "dēleō",
    "genitive": null,
    "gender": null,
    "english": "I destroy",
    "part_of_speech": "verb",
    "declension": null,
    "conjugation": 2,
    "topics": ["war/army"],
    "frequency_rank": 22
  },
  {
    "id": "discedo-01",
    "latin": "discēdō",
    "genitive": null,
    "gender": null,
    "english": "I depart, go away",
    "part_of_speech": "verb",
    "declension": null,
    "conjugation": null,
    "topics": ["travel", "daily-life"],
    "frequency_rank": 28
  },
  {
    "id": "do-01",
    "latin": "dō",
    "genitive": null,
    "gender": null,
    "english": "I give",
    "part_of_speech": "verb",
    "declension": null,
    "conjugation": 1,
    "topics": ["daily-life"],
    "frequency_rank": 9
  },
  {
    "id": "duco-01",
    "latin": "dūcō",
    "genitive": null,
    "gender": null,
    "english": "I lead; (here) I marry",
    "part_of_speech": "verb",
    "declension": null,
    "conjugation": null,
    "topics": ["family", "war/army"],
    "frequency_rank": 16
  },
  {
    "id": "eo-01",
    "latin": "eō",
    "genitive": null,
    "gender": null,
    "english": "I go",
    "part_of_speech": "verb",
    "declension": null,
    "conjugation": null,
    "topics": ["travel", "daily-life"],
    "frequency_rank": 11
  },
  {
    "id": "erro-01",
    "latin": "errō",
    "genitive": null,
    "gender": null,
    "english": "I wander, make a mistake",
    "part_of_speech": "verb",
    "declension": null,
    "conjugation": 1,
    "topics": ["travel", "daily-life"],
    "frequency_rank": 38
  },
  {
    "id": "faveo-01",
    "latin": "faveō",
    "genitive": null,
    "gender": null,
    "english": "I favour (+ dative)",
    "part_of_speech": "verb",
    "declension": null,
    "conjugation": 2,
    "topics": ["family", "daily-life"],
    "frequency_rank": 44
  },
  {
    "id": "festino-01",
    "latin": "festīnō",
    "genitive": null,
    "gender": null,
    "english": "I hurry",
    "part_of_speech": "verb",
    "declension": null,
    "conjugation": 1,
    "topics": ["travel", "daily-life"],
    "frequency_rank": 20
  },
  {
    "id": "fugio-01",
    "latin": "fugiō",
    "genitive": null,
    "gender": null,
    "english": "I flee, run away",
    "part_of_speech": "verb",
    "declension": null,
    "conjugation": null,
    "topics": ["war/army", "travel"],
    "frequency_rank": 21
  },
  {
    "id": "habeo-01",
    "latin": "habeō",
    "genitive": null,
    "gender": null,
    "english": "I have, hold",
    "part_of_speech": "verb",
    "declension": null,
    "conjugation": 2,
    "topics": ["daily-life"],
    "frequency_rank": 5
  },
  {
    "id": "habito-01",
    "latin": "habitō",
    "genitive": null,
    "gender": null,
    "english": "I live, dwell, inhabit",
    "part_of_speech": "verb",
    "declension": null,
    "conjugation": 1,
    "topics": ["daily-life", "family"],
    "frequency_rank": 13
  },
  {
    "id": "intro-01",
    "latin": "intrō",
    "genitive": null,
    "gender": null,
    "english": "I enter",
    "part_of_speech": "verb",
    "declension": null,
    "conjugation": 1,
    "topics": ["daily-life", "travel"],
    "frequency_rank": 17
  },
  {
    "id": "lacrimavit-01",
    "latin": "lacrimō",
    "genitive": null,
    "gender": null,
    "english": "I weep, cry",
    "part_of_speech": "verb",
    "declension": null,
    "conjugation": 1,
    "topics": ["daily-life", "family"],
    "frequency_rank": 39
  },
  {
    "id": "maneo-01",
    "latin": "māneō",
    "genitive": null,
    "gender": null,
    "english": "I remain, stay",
    "part_of_speech": "verb",
    "declension": null,
    "conjugation": 2,
    "topics": ["daily-life", "travel"],
    "frequency_rank": 27
  },
  {
    "id": "mitto-01",
    "latin": "mittō",
    "genitive": null,
    "gender": null,
    "english": "I send",
    "part_of_speech": "verb",
    "declension": null,
    "conjugation": null,
    "topics": ["war/army", "daily-life"],
    "frequency_rank": 12
  },
  {
    "id": "moneo-01",
    "latin": "moneō",
    "genitive": null,
    "gender": null,
    "english": "I warn, advise",
    "part_of_speech": "verb",
    "declension": null,
    "conjugation": 2,
    "topics": ["daily-life", "war/army"],
    "frequency_rank": 15
  },
  {
    "id": "muto-01",
    "latin": "mūtō",
    "genitive": null,
    "gender": null,
    "english": "I change",
    "part_of_speech": "verb",
    "declension": null,
    "conjugation": 1,
    "topics": ["daily-life"],
    "frequency_rank": 41
  },
  {
    "id": "navigo-01",
    "latin": "nāvigō",
    "genitive": null,
    "gender": null,
    "english": "I sail",
    "part_of_speech": "verb",
    "declension": null,
    "conjugation": 1,
    "topics": ["travel"],
    "frequency_rank": 30
  },
  {
    "id": "neco-01",
    "latin": "necō",
    "genitive": null,
    "gender": null,
    "english": "I kill",
    "part_of_speech": "verb",
    "declension": null,
    "conjugation": 1,
    "topics": ["war/army"],
    "frequency_rank": 23
  },
  {
    "id": "nuntio-01",
    "latin": "nūntiō",
    "genitive": null,
    "gender": null,
    "english": "I announce, report",
    "part_of_speech": "verb",
    "declension": null,
    "conjugation": 1,
    "topics": ["daily-life", "war/army"],
    "frequency_rank": 29
  },
  {
    "id": "paro-01",
    "latin": "parō",
    "genitive": null,
    "gender": null,
    "english": "I prepare, provide",
    "part_of_speech": "verb",
    "declension": null,
    "conjugation": 1,
    "topics": ["daily-life", "war/army"],
    "frequency_rank": 8
  },
  {
    "id": "pareo-01",
    "latin": "pāreō",
    "genitive": null,
    "gender": null,
    "english": "I obey (+ dative)",
    "part_of_speech": "verb",
    "declension": null,
    "conjugation": 2,
    "topics": ["family", "daily-life", "war/army"],
    "frequency_rank": 31
  },
  {
    "id": "peto-01",
    "latin": "petō",
    "genitive": null,
    "gender": null,
    "english": "I seek, make for, attack",
    "part_of_speech": "verb",
    "declension": null,
    "conjugation": null,
    "topics": ["war/army", "travel"],
    "frequency_rank": 24
  },
  {
    "id": "porto-01",
    "latin": "portō",
    "genitive": null,
    "gender": null,
    "english": "I carry",
    "part_of_speech": "verb",
    "declension": null,
    "conjugation": 1,
    "topics": ["daily-life", "war/army", "travel"],
    "frequency_rank": 6
  },
  {
    "id": "pugno-01",
    "latin": "pugnō",
    "genitive": null,
    "gender": null,
    "english": "I fight",
    "part_of_speech": "verb",
    "declension": null,
    "conjugation": 1,
    "topics": ["war/army"],
    "frequency_rank": 7
  },
  {
    "id": "rideo-01",
    "latin": "rideō",
    "genitive": null,
    "gender": null,
    "english": "I laugh, smile",
    "part_of_speech": "verb",
    "declension": null,
    "conjugation": 2,
    "topics": ["daily-life"],
    "frequency_rank": 37
  },
  {
    "id": "rego-01",
    "latin": "regō",
    "genitive": null,
    "gender": null,
    "english": "I rule, govern",
    "part_of_speech": "verb",
    "declension": null,
    "conjugation": null,
    "topics": ["war/army", "family"],
    "frequency_rank": 16
  },
  {
    "id": "respondeo-01",
    "latin": "respondeō",
    "genitive": null,
    "gender": null,
    "english": "I reply, answer",
    "part_of_speech": "verb",
    "declension": null,
    "conjugation": 2,
    "topics": ["daily-life"],
    "frequency_rank": 32
  },
  {
    "id": "rogo-01",
    "latin": "rogō",
    "genitive": null,
    "gender": null,
    "english": "I ask",
    "part_of_speech": "verb",
    "declension": null,
    "conjugation": 1,
    "topics": ["daily-life"],
    "frequency_rank": 26
  },
  {
    "id": "specto-01",
    "latin": "spectō",
    "genitive": null,
    "gender": null,
    "english": "I watch, look at",
    "part_of_speech": "verb",
    "declension": null,
    "conjugation": 1,
    "topics": ["daily-life"],
    "frequency_rank": 34
  },
  {
    "id": "taceo-01",
    "latin": "taceō",
    "genitive": null,
    "gender": null,
    "english": "I am silent, keep quiet",
    "part_of_speech": "verb",
    "declension": null,
    "conjugation": 2,
    "topics": ["daily-life"],
    "frequency_rank": 43
  },
  {
    "id": "terreo-01",
    "latin": "terreō",
    "genitive": null,
    "gender": null,
    "english": "I frighten, terrify",
    "part_of_speech": "verb",
    "declension": null,
    "conjugation": 2,
    "topics": ["war/army", "daily-life"],
    "frequency_rank": 35
  },
  {
    "id": "timeo-01",
    "latin": "timeō",
    "genitive": null,
    "gender": null,
    "english": "I fear, am afraid of",
    "part_of_speech": "verb",
    "declension": null,
    "conjugation": 2,
    "topics": ["war/army", "daily-life"],
    "frequency_rank": 13
  },
  {
    "id": "voco-01",
    "latin": "vocō",
    "genitive": null,
    "gender": null,
    "english": "I call, summon",
    "part_of_speech": "verb",
    "declension": null,
    "conjugation": 1,
    "topics": ["daily-life", "family"],
    "frequency_rank": 10
  },
  {
    "id": "video-01",
    "latin": "videō",
    "genitive": null,
    "gender": null,
    "english": "I see",
    "part_of_speech": "verb",
    "declension": null,
    "conjugation": 2,
    "topics": ["daily-life"],
    "frequency_rank": 3
  },
  {
    "id": "venio-01",
    "latin": "veniō",
    "genitive": null,
    "gender": null,
    "english": "I come",
    "part_of_speech": "verb",
    "declension": null,
    "conjugation": null,
    "topics": ["travel", "daily-life"],
    "frequency_rank": 6
  },
  {
    "id": "bonus-01",
    "latin": "bonus",
    "genitive": null,
    "gender": null,
    "english": "good",
    "part_of_speech": "adjective",
    "declension": null,
    "conjugation": null,
    "topics": ["daily-life"],
    "frequency_rank": 5
  },
  {
    "id": "malus-01",
    "latin": "malus",
    "genitive": null,
    "gender": null,
    "english": "bad, evil",
    "part_of_speech": "adjective",
    "declension": null,
    "conjugation": null,
    "topics": ["daily-life", "war/army"],
    "frequency_rank": 8
  },
  {
    "id": "magnus-01",
    "latin": "magnus",
    "genitive": null,
    "gender": null,
    "english": "great, large, big",
    "part_of_speech": "adjective",
    "declension": null,
    "conjugation": null,
    "topics": ["daily-life", "war/army"],
    "frequency_rank": 3
  },
  {
    "id": "parvus-01",
    "latin": "parvus",
    "genitive": null,
    "gender": null,
    "english": "small, little",
    "part_of_speech": "adjective",
    "declension": null,
    "conjugation": null,
    "topics": ["daily-life"],
    "frequency_rank": 16
  },
  {
    "id": "multus-01",
    "latin": "multus",
    "genitive": null,
    "gender": null,
    "english": "much, many",
    "part_of_speech": "adjective",
    "declension": null,
    "conjugation": null,
    "topics": ["daily-life"],
    "frequency_rank": 9
  },
  {
    "id": "longus-01",
    "latin": "longus",
    "genitive": null,
    "gender": null,
    "english": "long",
    "part_of_speech": "adjective",
    "declension": null,
    "conjugation": null,
    "topics": ["daily-life", "travel"],
    "frequency_rank": 20
  },
  {
    "id": "pulcher-01",
    "latin": "pulcher",
    "genitive": null,
    "gender": null,
    "english": "beautiful, handsome",
    "part_of_speech": "adjective",
    "declension": null,
    "conjugation": null,
    "topics": ["daily-life"],
    "frequency_rank": 22
  },
  {
    "id": "saevus-01",
    "latin": "saevus",
    "genitive": null,
    "gender": null,
    "english": "fierce, savage, cruel",
    "part_of_speech": "adjective",
    "declension": null,
    "conjugation": null,
    "topics": ["war/army", "daily-life"],
    "frequency_rank": 14
  },
  {
    "id": "laetus-01",
    "latin": "laetus",
    "genitive": null,
    "gender": null,
    "english": "happy, joyful",
    "part_of_speech": "adjective",
    "declension": null,
    "conjugation": null,
    "topics": ["daily-life"],
    "frequency_rank": 17
  },
  {
    "id": "miser-01",
    "latin": "miser",
    "genitive": null,
    "gender": null,
    "english": "wretched, unhappy, poor",
    "part_of_speech": "adjective",
    "declension": null,
    "conjugation": null,
    "topics": ["daily-life"],
    "frequency_rank": 18
  },
  {
    "id": "iratus-01",
    "latin": "īrātus",
    "genitive": null,
    "gender": null,
    "english": "angry",
    "part_of_speech": "adjective",
    "declension": null,
    "conjugation": null,
    "topics": ["daily-life"],
    "frequency_rank": 19
  },
  {
    "id": "aeger-01",
    "latin": "aeger",
    "genitive": null,
    "gender": null,
    "english": "sick, ill",
    "part_of_speech": "adjective",
    "declension": null,
    "conjugation": null,
    "topics": ["daily-life"],
    "frequency_rank": 36
  },
  {
    "id": "mortuus-01",
    "latin": "mortuus",
    "genitive": null,
    "gender": null,
    "english": "dead",
    "part_of_speech": "adjective",
    "declension": null,
    "conjugation": null,
    "topics": ["war/army", "daily-life"],
    "frequency_rank": 29
  },
  {
    "id": "omnis-01",
    "latin": "omnis",
    "genitive": null,
    "gender": null,
    "english": "all, every",
    "part_of_speech": "adjective",
    "declension": null,
    "conjugation": null,
    "topics": ["daily-life"],
    "frequency_rank": 11
  },
  {
    "id": "fortis-01",
    "latin": "fortis",
    "genitive": null,
    "gender": null,
    "english": "brave, strong",
    "part_of_speech": "adjective",
    "declension": null,
    "conjugation": null,
    "topics": ["war/army"],
    "frequency_rank": 21
  },
  {
    "id": "gravis-01",
    "latin": "gravis",
    "genitive": null,
    "gender": null,
    "english": "heavy, serious, grave",
    "part_of_speech": "adjective",
    "declension": null,
    "conjugation": null,
    "topics": ["daily-life", "war/army"],
    "frequency_rank": 33
  },
  {
    "id": "et-01",
    "latin": "et",
    "genitive": null,
    "gender": null,
    "english": "and; also",
    "part_of_speech": "conjunction",
    "declension": null,
    "conjugation": null,
    "topics": ["daily-life"],
    "frequency_rank": 1
  },
  {
    "id": "sed-01",
    "latin": "sed",
    "genitive": null,
    "gender": null,
    "english": "but",
    "part_of_speech": "conjunction",
    "declension": null,
    "conjugation": null,
    "topics": ["daily-life"],
    "frequency_rank": 4
  },
  {
    "id": "aut-01",
    "latin": "aut",
    "genitive": null,
    "gender": null,
    "english": "or",
    "part_of_speech": "conjunction",
    "declension": null,
    "conjugation": null,
    "topics": ["daily-life"],
    "frequency_rank": 15
  },
  {
    "id": "quod-01",
    "latin": "quod",
    "genitive": null,
    "gender": null,
    "english": "because",
    "part_of_speech": "conjunction",
    "declension": null,
    "conjugation": null,
    "topics": ["daily-life"],
    "frequency_rank": 10
  },
  {
    "id": "nam-01",
    "latin": "nam",
    "genitive": null,
    "gender": null,
    "english": "for, because",
    "part_of_speech": "conjunction",
    "declension": null,
    "conjugation": null,
    "topics": ["daily-life"],
    "frequency_rank": 13
  },
  {
    "id": "tamen-01",
    "latin": "tamen",
    "genitive": null,
    "gender": null,
    "english": "however, nevertheless",
    "part_of_speech": "conjunction",
    "declension": null,
    "conjugation": null,
    "topics": ["daily-life"],
    "frequency_rank": 9
  },
  {
    "id": "igitur-01",
    "latin": "igitur",
    "genitive": null,
    "gender": null,
    "english": "therefore, and so",
    "part_of_speech": "conjunction",
    "declension": null,
    "conjugation": null,
    "topics": ["daily-life"],
    "frequency_rank": 12
  },
  {
    "id": "itaque-01",
    "latin": "itaque",
    "genitive": null,
    "gender": null,
    "english": "and so, therefore",
    "part_of_speech": "conjunction",
    "declension": null,
    "conjugation": null,
    "topics": ["daily-life"],
    "frequency_rank": 16
  },
  {
    "id": "postquam-01",
    "latin": "postquam",
    "genitive": null,
    "gender": null,
    "english": "after, when",
    "part_of_speech": "conjunction",
    "declension": null,
    "conjugation": null,
    "topics": ["daily-life"],
    "frequency_rank": 18
  },
  {
    "id": "ubi-01",
    "latin": "ubi",
    "genitive": null,
    "gender": null,
    "english": "where, when",
    "part_of_speech": "conjunction",
    "declension": null,
    "conjugation": null,
    "topics": ["daily-life", "travel"],
    "frequency_rank": 14
  },
  {
    "id": "ad-01",
    "latin": "ad",
    "genitive": null,
    "gender": null,
    "english": "to, towards, at (+ accusative)",
    "part_of_speech": "preposition",
    "declension": null,
    "conjugation": null,
    "topics": ["travel", "daily-life"],
    "frequency_rank": 2
  },
  {
    "id": "contra-01",
    "latin": "contrā",
    "genitive": null,
    "gender": null,
    "english": "against (+ accusative)",
    "part_of_speech": "preposition",
    "declension": null,
    "conjugation": null,
    "topics": ["war/army", "daily-life"],
    "frequency_rank": 11
  },
  {
    "id": "cum-01",
    "latin": "cum",
    "genitive": null,
    "gender": null,
    "english": "with (+ ablative)",
    "part_of_speech": "preposition",
    "declension": null,
    "conjugation": null,
    "topics": ["daily-life"],
    "frequency_rank": 6
  },
  {
    "id": "de-01",
    "latin": "dē",
    "genitive": null,
    "gender": null,
    "english": "about, concerning; down from (+ ablative)",
    "part_of_speech": "preposition",
    "declension": null,
    "conjugation": null,
    "topics": ["daily-life"],
    "frequency_rank": 14
  },
  {
    "id": "e-01",
    "latin": "ē / ex",
    "genitive": null,
    "gender": null,
    "english": "out of, from (+ ablative)",
    "part_of_speech": "preposition",
    "declension": null,
    "conjugation": null,
    "topics": ["travel", "daily-life"],
    "frequency_rank": 8
  },
  {
    "id": "in-01",
    "latin": "in",
    "genitive": null,
    "gender": null,
    "english": "into, onto (+ acc.); in, on (+ abl.)",
    "part_of_speech": "preposition",
    "declension": null,
    "conjugation": null,
    "topics": ["daily-life", "travel"],
    "frequency_rank": 3
  },
  {
    "id": "per-01",
    "latin": "per",
    "genitive": null,
    "gender": null,
    "english": "through, along (+ accusative)",
    "part_of_speech": "preposition",
    "declension": null,
    "conjugation": null,
    "topics": ["travel", "daily-life"],
    "frequency_rank": 10
  },
  {
    "id": "post-01",
    "latin": "post",
    "genitive": null,
    "gender": null,
    "english": "after, behind (+ accusative)",
    "part_of_speech": "preposition",
    "declension": null,
    "conjugation": null,
    "topics": ["daily-life", "travel"],
    "frequency_rank": 13
  },
  {
    "id": "pro-01",
    "latin": "prō",
    "genitive": null,
    "gender": null,
    "english": "for, on behalf of (+ ablative)",
    "part_of_speech": "preposition",
    "declension": null,
    "conjugation": null,
    "topics": ["war/army", "daily-life"],
    "frequency_rank": 15
  },
  {
    "id": "propter-01",
    "latin": "propter",
    "genitive": null,
    "gender": null,
    "english": "because of, on account of (+ accusative)",
    "part_of_speech": "preposition",
    "declension": null,
    "conjugation": null,
    "topics": ["daily-life"],
    "frequency_rank": 20
  },
  {
    "id": "sine-01",
    "latin": "sine",
    "genitive": null,
    "gender": null,
    "english": "without (+ ablative)",
    "part_of_speech": "preposition",
    "declension": null,
    "conjugation": null,
    "topics": ["daily-life"],
    "frequency_rank": 17
  },
  {
    "id": "sub-01",
    "latin": "sub",
    "genitive": null,
    "gender": null,
    "english": "under (+ abl./acc.)",
    "part_of_speech": "preposition",
    "declension": null,
    "conjugation": null,
    "topics": ["daily-life", "nature"],
    "frequency_rank": 22
  },
  {
    "id": "trans-01",
    "latin": "trāns",
    "genitive": null,
    "gender": null,
    "english": "across (+ accusative)",
    "part_of_speech": "preposition",
    "declension": null,
    "conjugation": null,
    "topics": ["travel"],
    "frequency_rank": 19
  },
  {
    "id": "bene-01",
    "latin": "bene",
    "genitive": null,
    "gender": null,
    "english": "well",
    "part_of_speech": "adverb",
    "declension": null,
    "conjugation": null,
    "topics": ["daily-life"],
    "frequency_rank": 11
  },
  {
    "id": "celeriter-01",
    "latin": "celeriter",
    "genitive": null,
    "gender": null,
    "english": "quickly, swiftly",
    "part_of_speech": "adverb",
    "declension": null,
    "conjugation": null,
    "topics": ["daily-life", "travel"],
    "frequency_rank": 14
  },
  {
    "id": "deinde-01",
    "latin": "deinde",
    "genitive": null,
    "gender": null,
    "english": "then, next, afterwards",
    "part_of_speech": "adverb",
    "declension": null,
    "conjugation": null,
    "topics": ["daily-life"],
    "frequency_rank": 16
  },
  {
    "id": "diu-01",
    "latin": "diū",
    "genitive": null,
    "gender": null,
    "english": "for a long time",
    "part_of_speech": "adverb",
    "declension": null,
    "conjugation": null,
    "topics": ["daily-life"],
    "frequency_rank": 12
  },
  {
    "id": "frustra-01",
    "latin": "frūstrā",
    "genitive": null,
    "gender": null,
    "english": "in vain",
    "part_of_speech": "adverb",
    "declension": null,
    "conjugation": null,
    "topics": ["daily-life", "war/army"],
    "frequency_rank": 26
  },
  {
    "id": "hic-01",
    "latin": "hīc",
    "genitive": null,
    "gender": null,
    "english": "here",
    "part_of_speech": "adverb",
    "declension": null,
    "conjugation": null,
    "topics": ["travel", "daily-life"],
    "frequency_rank": 18
  },
  {
    "id": "iam-01",
    "latin": "iam",
    "genitive": null,
    "gender": null,
    "english": "now, already",
    "part_of_speech": "adverb",
    "declension": null,
    "conjugation": null,
    "topics": ["daily-life"],
    "frequency_rank": 9
  },
  {
    "id": "magnopere-01",
    "latin": "magnopere",
    "genitive": null,
    "gender": null,
    "english": "greatly, very much",
    "part_of_speech": "adverb",
    "declension": null,
    "conjugation": null,
    "topics": ["daily-life"],
    "frequency_rank": 15
  },
  {
    "id": "mox-01",
    "latin": "mox",
    "genitive": null,
    "gender": null,
    "english": "soon",
    "part_of_speech": "adverb",
    "declension": null,
    "conjugation": null,
    "topics": ["daily-life"],
    "frequency_rank": 17
  },
  {
    "id": "non-01",
    "latin": "nōn",
    "genitive": null,
    "gender": null,
    "english": "not",
    "part_of_speech": "adverb",
    "declension": null,
    "conjugation": null,
    "topics": ["daily-life"],
    "frequency_rank": 2
  },
  {
    "id": "nunc-01",
    "latin": "nunc",
    "genitive": null,
    "gender": null,
    "english": "now",
    "part_of_speech": "adverb",
    "declension": null,
    "conjugation": null,
    "topics": ["daily-life"],
    "frequency_rank": 13
  },
  {
    "id": "olim-01",
    "latin": "olim",
    "genitive": null,
    "gender": null,
    "english": "once, once upon a time",
    "part_of_speech": "adverb",
    "declension": null,
    "conjugation": null,
    "topics": ["daily-life"],
    "frequency_rank": 10
  },
  {
    "id": "saepe-01",
    "latin": "saepe",
    "genitive": null,
    "gender": null,
    "english": "often",
    "part_of_speech": "adverb",
    "declension": null,
    "conjugation": null,
    "topics": ["daily-life"],
    "frequency_rank": 8
  },
  {
    "id": "semper-01",
    "latin": "semper",
    "genitive": null,
    "gender": null,
    "english": "always",
    "part_of_speech": "adverb",
    "declension": null,
    "conjugation": null,
    "topics": ["daily-life"],
    "frequency_rank": 7
  },
  {
    "id": "sic-01",
    "latin": "sīc",
    "genitive": null,
    "gender": null,
    "english": "thus, in this way",
    "part_of_speech": "adverb",
    "declension": null,
    "conjugation": null,
    "topics": ["daily-life"],
    "frequency_rank": 19
  },
  {
    "id": "statim-01",
    "latin": "statim",
    "genitive": null,
    "gender": null,
    "english": "immediately, at once",
    "part_of_speech": "adverb",
    "declension": null,
    "conjugation": null,
    "topics": ["daily-life"],
    "frequency_rank": 6
  },
  {
    "id": "subito-01",
    "latin": "subitō",
    "genitive": null,
    "gender": null,
    "english": "suddenly",
    "part_of_speech": "adverb",
    "declension": null,
    "conjugation": null,
    "topics": ["daily-life", "war/army"],
    "frequency_rank": 20
  },
  {
    "id": "tandem-01",
    "latin": "tandem",
    "genitive": null,
    "gender": null,
    "english": "at last, finally",
    "part_of_speech": "adverb",
    "declension": null,
    "conjugation": null,
    "topics": ["daily-life"],
    "frequency_rank": 21
  },
  {
    "id": "hic-02",
    "latin": "hic",
    "genitive": null,
    "gender": null,
    "english": "this, he, she, it",
    "part_of_speech": "pronoun",
    "declension": null,
    "conjugation": null,
    "topics": ["daily-life"],
    "frequency_rank": 5
  },
  {
    "id": "ego-01",
    "latin": "ego",
    "genitive": null,
    "gender": null,
    "english": "I",
    "part_of_speech": "pronoun",
    "declension": null,
    "conjugation": null,
    "topics": ["daily-life"],
    "frequency_rank": 7
  },
  {
    "id": "is-01",
    "latin": "is",
    "genitive": null,
    "gender": null,
    "english": "he, she, it; that",
    "part_of_speech": "pronoun",
    "declension": null,
    "conjugation": null,
    "topics": ["daily-life"],
    "frequency_rank": 4
  },
  {
    "id": "qui-01",
    "latin": "quī",
    "genitive": null,
    "gender": null,
    "english": "who, which, that",
    "part_of_speech": "pronoun",
    "declension": null,
    "conjugation": null,
    "topics": ["daily-life"],
    "frequency_rank": 6
  },
  {
    "id": "unus-01",
    "latin": "ūnus",
    "genitive": null,
    "gender": null,
    "english": "one",
    "part_of_speech": "numeral",
    "declension": null,
    "conjugation": null,
    "topics": ["daily-life"],
    "frequency_rank": 25
  },
  {
    "id": "duo-01",
    "latin": "duo",
    "genitive": null,
    "gender": null,
    "english": "two",
    "part_of_speech": "numeral",
    "declension": null,
    "conjugation": null,
    "topics": ["daily-life"],
    "frequency_rank": 28
  },
  {
    "id": "tres-01",
    "latin": "trēs",
    "genitive": null,
    "gender": null,
    "english": "three",
    "part_of_speech": "numeral",
    "declension": null,
    "conjugation": null,
    "topics": ["daily-life"],
    "frequency_rank": 31
  },
  {
    "id": "quattuor-01",
    "latin": "quattuor",
    "genitive": null,
    "gender": null,
    "english": "four",
    "part_of_speech": "numeral",
    "declension": null,
    "conjugation": null,
    "topics": ["daily-life"],
    "frequency_rank": 40
  },
  {
    "id": "quinque-01",
    "latin": "quīnque",
    "genitive": null,
    "gender": null,
    "english": "five",
    "part_of_speech": "numeral",
    "declension": null,
    "conjugation": null,
    "topics": ["daily-life"],
    "frequency_rank": 42
  },
  {
    "id": "decem-01",
    "latin": "decem",
    "genitive": null,
    "gender": null,
    "english": "ten",
    "part_of_speech": "numeral",
    "declension": null,
    "conjugation": null,
    "topics": ["daily-life"],
    "frequency_rank": 44
  },
  {
    "id": "centum-01",
    "latin": "centum",
    "genitive": null,
    "gender": null,
    "english": "one hundred",
    "part_of_speech": "numeral",
    "declension": null,
    "conjugation": null,
    "topics": ["daily-life"],
    "frequency_rank": 46
  },
  {
    "id": "dea-01",
    "latin": "dea",
    "genitive": "deae",
    "gender": "f",
    "english": "goddess",
    "part_of_speech": "noun",
    "declension": 1,
    "conjugation": null,
    "topics": ["gods"],
    "frequency_rank": 23
  },
  {
    "id": "ara-01",
    "latin": "āra",
    "genitive": "ārae",
    "gender": "f",
    "english": "altar",
    "part_of_speech": "noun",
    "declension": 1,
    "conjugation": null,
    "topics": ["gods", "daily-life"],
    "frequency_rank": 37
  },
  {
    "id": "sagitta-01",
    "latin": "sagitta",
    "genitive": "sagittae",
    "gender": "f",
    "english": "arrow",
    "part_of_speech": "noun",
    "declension": 1,
    "conjugation": null,
    "topics": ["war/army"],
    "frequency_rank": 45
  },
  {
    "id": "corona-01",
    "latin": "corōna",
    "genitive": "corōnae",
    "gender": "f",
    "english": "crown, garland",
    "part_of_speech": "noun",
    "declension": 1,
    "conjugation": null,
    "topics": ["gods", "daily-life"],
    "frequency_rank": 48
  },
  {
    "id": "arma-01",
    "latin": "arma",
    "genitive": "armōrum",
    "gender": "n",
    "english": "arms, weapons (pl.)",
    "part_of_speech": "noun",
    "declension": 2,
    "conjugation": null,
    "topics": ["war/army"],
    "frequency_rank": 27
  },
  {
    "id": "castra-01",
    "latin": "castra",
    "genitive": "castrōrum",
    "gender": "n",
    "english": "camp (pl.)",
    "part_of_speech": "noun",
    "declension": 2,
    "conjugation": null,
    "topics": ["war/army"],
    "frequency_rank": 32
  },
  {
    "id": "porta-01",
    "latin": "porta",
    "genitive": "portae",
    "gender": "f",
    "english": "gate",
    "part_of_speech": "noun",
    "declension": 1,
    "conjugation": null,
    "topics": ["war/army", "travel", "daily-life"],
    "frequency_rank": 30
  },
  {
    "id": "casa-01",
    "latin": "casa",
    "genitive": "casae",
    "gender": "f",
    "english": "hut, cottage",
    "part_of_speech": "noun",
    "declension": 1,
    "conjugation": null,
    "topics": ["daily-life"],
    "frequency_rank": 47
  },
  {
    "id": "dux-02",
    "latin": "dux",
    "genitive": "ducis",
    "gender": "m",
    "english": "leader, general",
    "part_of_speech": "noun",
    "declension": 3,
    "conjugation": null,
    "topics": ["war/army"],
    "frequency_rank": 18
  },
  {
    "id": "corpus-01",
    "latin": "corpus",
    "genitive": "corporis",
    "gender": "n",
    "english": "body",
    "part_of_speech": "noun",
    "declension": 3,
    "conjugation": null,
    "topics": ["daily-life"],
    "frequency_rank": 38
  },
  {
    "id": "iter-01",
    "latin": "iter",
    "genitive": "itineris",
    "gender": "n",
    "english": "journey, march, route",
    "part_of_speech": "noun",
    "declension": 3,
    "conjugation": null,
    "topics": ["travel", "war/army"],
    "frequency_rank": 34
  },
  {
    "id": "mons-01",
    "latin": "mōns",
    "genitive": "montis",
    "gender": "m",
    "english": "mountain, hill",
    "part_of_speech": "noun",
    "declension": 3,
    "conjugation": null,
    "topics": ["nature", "travel"],
    "frequency_rank": 41
  },
  {
    "id": "pons-01",
    "latin": "pōns",
    "genitive": "pontis",
    "gender": "m",
    "english": "bridge",
    "part_of_speech": "noun",
    "declension": 3,
    "conjugation": null,
    "topics": ["travel", "war/army"],
    "frequency_rank": 43
  },
  {
    "id": "princeps-01",
    "latin": "prīnceps",
    "genitive": "prīncipis",
    "gender": "m",
    "english": "chief, leader, emperor",
    "part_of_speech": "noun",
    "declension": 3,
    "conjugation": null,
    "topics": ["war/army", "family"],
    "frequency_rank": 46
  },
  {
    "id": "senex-01",
    "latin": "senex",
    "genitive": "senis",
    "gender": "m",
    "english": "old man",
    "part_of_speech": "noun",
    "declension": 3,
    "conjugation": null,
    "topics": ["family", "daily-life"],
    "frequency_rank": 48
  },
  {
    "id": "hostis-01",
    "latin": "hostis",
    "genitive": "hostis",
    "gender": "m",
    "english": "enemy (in war)",
    "part_of_speech": "noun",
    "declension": 3,
    "conjugation": null,
    "topics": ["war/army"],
    "frequency_rank": 22
  },
  {
    "id": "mater-01",
    "latin": "māter",
    "genitive": "mātris",
    "gender": "f",
    "english": "mother",
    "part_of_speech": "noun",
    "declension": 3,
    "conjugation": null,
    "topics": ["family", "gods"],
    "frequency_rank": 12
  },
  {
    "id": "frater-01",
    "latin": "frāter",
    "genitive": "frātris",
    "gender": "m",
    "english": "brother",
    "part_of_speech": "noun",
    "declension": 3,
    "conjugation": null,
    "topics": ["family"],
    "frequency_rank": 24
  },
  {
    "id": "soror-01",
    "latin": "soror",
    "genitive": "sorōris",
    "gender": "f",
    "english": "sister",
    "part_of_speech": "noun",
    "declension": 3,
    "conjugation": null,
    "topics": ["family"],
    "frequency_rank": 29
  },
  {
    "id": "nox-01",
    "latin": "nox",
    "genitive": "noctis",
    "gender": "f",
    "english": "night",
    "part_of_speech": "noun",
    "declension": 3,
    "conjugation": null,
    "topics": ["nature", "daily-life"],
    "frequency_rank": 39
  },
  {
    "id": "pax-01",
    "latin": "pāx",
    "genitive": "pācis",
    "gender": "f",
    "english": "peace",
    "part_of_speech": "noun",
    "declension": 3,
    "conjugation": null,
    "topics": ["war/army"],
    "frequency_rank": 33
  },
  {
    "id": "audax-01",
    "latin": "audāx",
    "genitive": null,
    "gender": null,
    "english": "bold, daring",
    "part_of_speech": "adjective",
    "declension": null,
    "conjugation": null,
    "topics": ["war/army", "daily-life"],
    "frequency_rank": 44
  },
  {
    "id": "celer-01",
    "latin": "celer",
    "genitive": null,
    "gender": null,
    "english": "swift, quick",
    "part_of_speech": "adjective",
    "declension": null,
    "conjugation": null,
    "topics": ["daily-life", "travel"],
    "frequency_rank": 45
  },
  {
    "id": "fessus-01",
    "latin": "fessus",
    "genitive": null,
    "gender": null,
    "english": "tired, weary",
    "part_of_speech": "adjective",
    "declension": null,
    "conjugation": null,
    "topics": ["daily-life", "war/army"],
    "frequency_rank": 42
  }
]
